trustflow/attestation/__init__.py
trustflow/attestation/common.py
trustflow/attestation/generation/__init__.py
trustflow/attestation/generation/api.py
trustflow/attestation/generation/generator.so
trustflow/attestation/verification/__init__.py
trustflow/attestation/verification/api.py
trustflow/attestation/verification/verifier.cpython-310-x86_64-linux-gnu.so
trustflow_tdx_generation-0.3.0.dev20250924.dist-info/licenses/LICENSE
trustflow_tdx_generation-0.3.0.dev20250924.dist-info/METADATA
trustflow_tdx_generation-0.3.0.dev20250924.dist-info/WHEEL
trustflow_tdx_generation-0.3.0.dev20250924.dist-info/top_level.txt
trustflow_tdx_generation-0.3.0.dev20250924.dist-info/RECORD
